cutracer/validation/schema_loader.py
cutracer/validation/schemas/__init__.py
cutracer/validation/schemas/mem_trace.schema.json
cutracer/validation/schemas/opcode_only.schema.json
cutracer/validation/schemas/reg_trace.schema.json
cutracer-0.1.dev23.dist-info/METADATA
cutracer-0.1.dev23.dist-info/WHEEL
cutracer-0.1.dev23.dist-info/top_level.txt
cutracer-0.1.dev23.dist-info/RECORD
