Metadata-Version: 2.4
Name: cutracer
Version: 0.1.dev23
Summary: Python tools for CUTracer trace validation and analysis
Author-email: Yueming Hao <yhao@meta.com>
License-Expression: MIT
Project-URL: Homepage, https://github.com/facebookresearch/CUTracer
Project-URL: Bug Tracker, https://github.com/facebookresearch/CUTracer/issues
Requires-Python: >=3.10
Requires-Dist: jsonschema>=4.0.0
Requires-Dist: importlib_resources>=5.0.0; python_version < "3.11"
Provides-Extra: dev
Requires-Dist: pytest>=7.0.0; extra == "dev"
Requires-Dist: pytest-cov>=4.0.0; extra == "dev"
Requires-Dist: mypy>=1.0.0; extra == "dev"
Requires-Dist: black>=22.0.0; extra == "dev"
Requires-Dist: ruff>=0.1.0; extra == "dev"
Requires-Dist: ufmt>=2.0.0; extra == "dev"
Requires-Dist: usort>=1.0.0; extra == "dev"
